pseudocode_summarizer/__init__.py
pseudocode_summarizer/chatbot.py
pseudocode_summarizer/classifier.py
pseudocode_summarizer/cli.py
pseudocode_summarizer/file_handler.py
pseudocode_summarizer/mapper.py
pseudocode_summarizer/summarize.py
pseudocode_summarizer/summarizer.py
pseudocode_summarizer-0.1.1.dist-info/entry_points.txt
pseudocode_summarizer-0.1.1.dist-info/LICENSE
pseudocode_summarizer-0.1.1.dist-info/METADATA
pseudocode_summarizer-0.1.1.dist-info/WHEEL
pseudocode_summarizer-0.1.1.dist-info/RECORD
