Metadata-Version: 2.1
Name: pseudocode-summarizer
Version: 0.1.1
Summary: 
License: MIT
Author: Christopher Carroll Smith
Author-email: 75859865+chriscarrollsmith@users.noreply.github.com
Requires-Python: >=3.11,<4.0
Classifier: License :: OSI Approved :: MIT License
Classifier: Programming Language :: Python :: 3
Classifier: Programming Language :: Python :: 3.11
Requires-Dist: click (>=8.1.7,<9.0.0)
Requires-Dist: langchain (>=0.0.272,<0.0.273)
Requires-Dist: openai (>=0.28.0,<0.29.0)
Requires-Dist: pathspec (>=0.11.2,<0.12.0)
Requires-Dist: pydantic (>=2.3.0,<3.0.0)
Requires-Dist: python-dotenv (>=1.0.0,<2.0.0)
